akun_tools/scraper.py
akun_tools-0.1.2.dist-info/entry_points.txt
akun_tools-0.1.2.dist-info/WHEEL
akun_tools-0.1.2.dist-info/METADATA
akun_tools-0.1.2.dist-info/RECORD
